{
	"fileVersion": 1,
	"versions": {
		"bindbc-loader": "1.0.3",
		"bindbc-lua": "0.5.1",
		"bindbc-sdl": "1.1.3",
		"bindbc-spout2": "0.1.1",
		"ddbus": "3.0.0-beta.2",
		"diet-ng": "1.8.2",
		"dportals": "0.1.0",
		"dunit": "1.0.16",
		"eventcore": "0.9.35",
		"facetrack-d": "0.7.8",
		"fghj": "1.0.2",
		"i18n-d": "1.0.2",
		"i2d-imgui": "0.8.0+build.5.ga27fcbb",
		"i2d-opengl": "1.0.0",
		"imagefmt": "2.1.2",
		"inmath": "1.0.6",
		"lumars": "1.6.1",
		"mir-algorithm": "3.22.1",
		"mir-core": "1.7.1",
		"mir-linux-kernel": "1.0.1",
		"nijilive": "0.0.0+build.659.808fcc2",
		"nijiui": "0.0.0+build.80.f2d562f",
		"openssl": "3.3.4",
		"openssl-static": "1.0.5+3.0.8",
		"silly": "1.1.1",
		"stdx-allocator": "2.77.5",
		"taggedalgebraic": "0.11.23",
		"tinyfiledialogs": "0.10.1",
		"vibe-container": "1.3.1",
		"vibe-core": "2.9.5",
		"vibe-d": "0.9.8",
		"vmc-d": "1.1.3"
	}
}
